bopomo/__init__.py
bopomo/bopomo.py
bopomo/data/bopomo_seg_words.csv
bopomo/data/bopomo_word.csv
bopomo/data/bopomo_words.csv
bopomo/data/words_list.txt
bopomo/model/bopomo.crfsuite
bopomo-0.0.8.dist-info/METADATA
bopomo-0.0.8.dist-info/RECORD
bopomo-0.0.8.dist-info/WHEEL
bopomo-0.0.8.dist-info/top_level.txt
