Metadata-Version: 2.1
Name: bopomo
Version: 0.0.8
Summary: This is a package to translate a chinese sentence into bopomofo letters
Home-page: UNKNOWN
Author: Hsin-Min Lu, Jian-Long Liao
Author-email: slingan127@gmail.com
License: UNKNOWN
Platform: UNKNOWN
Classifier: License :: OSI Approved :: GNU General Public License v3 or later (GPLv3+)
Classifier: Programming Language :: Python :: 3.5
Classifier: Programming Language :: Python :: 3.6
Requires-Python: >=3
Requires-Dist: python-crfsuite
Requires-Dist: jieba
